{
	"files": [
		{
			"path": "sardinia.cpp",
			"bookmarks": [
				{
					"line": 0,
					"column": 0,
					"label": ""
				},
				{
					"line": 10,
					"column": 0,
					"label": ""
				},
				{
					"line": 53,
					"column": 0,
					"label": ""
				},
				{
					"line": 133,
					"column": 0,
					"label": ""
				}
			]
		},
		{
			"path": "hardware.h",
			"bookmarks": [
				{
					"line": 0,
					"column": 0,
					"label": ""
				},
				{
					"line": 50,
					"column": 0,
					"label": ""
				},
				{
					"line": 59,
					"column": 0,
					"label": ""
				},
				{
					"line": 72,
					"column": 0,
					"label": ""
				}
			]
		}
	]
}